{
  "version": 1,
  "serviceConfiguration": {
    "apiName": "BaitBattle",
    "serviceName": "AppSync",
    "gqlSchemaPath": "/tmp/amplify-a0fbfa40-ee76-4442-bb93-fdd7b5b270ef/amplify/backend/api/BaitBattle/schema.graphql",
    "defaultAuthType": {
      "mode": "API_KEY",
      "keyDescription": "api key description",
      "expirationTime": 30
    },
    "additionalAuthTypes": [
      {
        "mode": "AWS_IAM"
      }
    ],
    "conflictResolution": {
      "defaultResolutionStrategy": {
        "type": "AUTOMERGE"
      }
    }
  }
}